README.md
setup.py
Vic_Lim_WX.egg-info/PKG-INFO
Vic_Lim_WX.egg-info/SOURCES.txt
Vic_Lim_WX.egg-info/dependency_links.txt
Vic_Lim_WX.egg-info/top_level.txt
vic_lim_wx/__init__.py
vic_lim_wx/custom_logger/__init__.py
vic_lim_wx/custom_logger/private_repo/__init__.py
vic_lim_wx/custom_logger/private_repo/color_ascii.py
vic_lim_wx/custom_logger/private_repo/colored_formatter.py
vic_lim_wx/custom_logger/private_repo/error_configuration.py
vic_lim_wx/custom_logger/public/__init__.py
vic_lim_wx/custom_logger/public/logger_config.py
vic_lim_wx/custom_logger/public/logger_config_factory.py
vic_lim_wx/custom_logger/public/logger_custom.py
vic_lim_wx/custom_logger/public/vic_custom_logger.py
vic_lim_wx/database_manager/__init__.py
vic_lim_wx/database_manager/databasemanager.py
vic_lim_wx/file_manager/__init__.py
vic_lim_wx/file_manager/exception.py
vic_lim_wx/file_manager/private_repo/__init__.py
vic_lim_wx/file_manager/private_repo/_file_manager_api.py
vic_lim_wx/file_manager/private_repo/_file_manager_csv.py
vic_lim_wx/file_manager/private_repo/_file_manager_json.py
vic_lim_wx/file_manager/private_repo/_file_manager_sqlite.py
vic_lim_wx/file_manager/public/__init__.py
vic_lim_wx/file_manager/public/file_manager_base.py
vic_lim_wx/file_manager/public/file_manager_factory.py